jTWA/__init__.py
jTWA/integrate.py
jTWA/util.py
jTWA/visualization.py
jTWA/spin1/__init__.py
jTWA/spin1/hamiltonian.py
jTWA/spin1/initState.py
jTWA/spin1/observables.py
jtwa-0.0.4.dist-info/METADATA
jtwa-0.0.4.dist-info/WHEEL
jtwa-0.0.4.dist-info/licenses/LICENSE
jtwa-0.0.4.dist-info/RECORD
